espai/__init__.py
espai/cli.py
espai/gemini_client.py
espai/models.py
espai/rate_limiter.py
espai/scraper.py
espai/search_providers/__init__.py
espai/search_providers/exa.py
espai/search_providers/google.py
espai-0.2.5.dist-info/LICENSE
espai-0.2.5.dist-info/METADATA
espai-0.2.5.dist-info/WHEEL
espai-0.2.5.dist-info/entry_points.txt
espai-0.2.5.dist-info/RECORD
